full_month/__init__.py
full_month/date_handler.py
full_month-0.0.4.dist-info/LICENSE
full_month-0.0.4.dist-info/METADATA
full_month-0.0.4.dist-info/WHEEL
full_month-0.0.4.dist-info/top_level.txt
full_month-0.0.4.dist-info/RECORD
