Metadata-Version: 2.1
Name: full-month
Version: 0.0.4
Summary: show the full display of one month of 5 row * 7 day format,starting from Monday and ending on Sunday.
Home-page: UNKNOWN
Author: neomaple
Author-email: xinkun7778@163.com
License: None
Platform: UNKNOWN
